{
    "type": "object",
    "properties": {
        "contact_id": {
            "type": "string",
            "format": "uuid"
        },
        "project_id": {
            "required": false,
            "type": "string",
            "format": "uuid"
        },
        "invoice_number": {
            "type": "string"
        },
        "offer_number": {
            "type": "string"
        },
        "is_draft": {
            "type": "integer",
            "enum": [
                0,
                1
            ]
        },
        "is_offer": {
            "type": "integer",
            "enum": [
                0,
                1
            ]
        },
        "is_locked": {
            "type": "integer",
            "enum": [
                0,
                1
            ]
        },
        "date_from": {
            "type": "string",
            "format": "date"
        },
        "date_to": {
            "type": "string",
            "format": "date"
        },
        "issued_date": {
            "type": "string",
            "format": "date"
        }
    }
}